korapay_client/__init__.py
korapay_client/_metadata.py
korapay_client/base_clients.py
korapay_client/exceptions.py
korapay_client/utils.py
korapay_client/clients/__init__.py
korapay_client/clients/async_client.py
korapay_client/clients/client_method_parameter_validator.py
korapay_client/clients/sync_client.py
korapay_client/enums/__init__.py
korapay_client/enums/internal.py
korapay_client/enums/public.py
korapay_client/models/__init__.py
korapay_client/models/internal.py
korapay_client/models/public.py
korapay_client-0.1.0.dist-info/METADATA
korapay_client-0.1.0.dist-info/WHEEL
korapay_client-0.1.0.dist-info/licenses/LICENSE
korapay_client-0.1.0.dist-info/RECORD
